nudb_config/__init__.py
nudb_config/config.py
nudb_config/config_tomls/datasets_in.toml
nudb_config/config_tomls/datasets_shared.toml
nudb_config/config_tomls/options.toml
nudb_config/config_tomls/paths.toml
nudb_config/config_tomls/settings.toml
nudb_config/config_tomls/variables.toml
nudb_config/config_tomls/variables_derived.toml
nudb_config/config_tomls/variables_label.toml
nudb_config/config_tomls/variables_outdated.toml
nudb_config/py.typed
nudb_config/pydantic/__init__.py
nudb_config/pydantic/datasets.py
nudb_config/pydantic/dotmap.py
nudb_config/pydantic/load.py
nudb_config/pydantic/options.py
nudb_config/pydantic/paths.py
nudb_config/pydantic/settings.py
nudb_config/pydantic/variables.py
ssb_nudb_config-2026.1.10.dist-info/METADATA
ssb_nudb_config-2026.1.10.dist-info/WHEEL
ssb_nudb_config-2026.1.10.dist-info/licenses/LICENSE
ssb_nudb_config-2026.1.10.dist-info/RECORD
