Metadata-Version: 2.4
Name: ssb-nudb-config
Version: 2026.1.10
Summary: The config for NUDB - Nasjonal utdanningsdatabase
License-Expression: MIT
License-File: LICENSE
Author: Markus Storeide
Author-email: rku@ssb.no
Maintainer: Statistics Norway, Education statistics Department (360)
Requires-Python: >=3.11
Classifier: Development Status :: 3 - Alpha
Classifier: Programming Language :: Python :: 3
Classifier: Programming Language :: Python :: 3.11
Classifier: Programming Language :: Python :: 3.12
Classifier: Programming Language :: Python :: 3.13
Classifier: Programming Language :: Python :: 3.14
Requires-Dist: ipykernel (>=7.0.0)
Requires-Dist: pydantic (>=2.5)
Requires-Dist: ssb-klass-python (>=1.0.4)
Project-URL: Changelog, https://github.com/statisticsnorway/ssb-nudb-config/releases
Project-URL: Documentation, https://statisticsnorway.github.io/ssb-nudb-config
Project-URL: Homepage, https://github.com/statisticsnorway/ssb-nudb-config
Project-URL: Repository, https://github.com/statisticsnorway/ssb-nudb-config
